{
    "symbol": "DXCM",
    "tournament": 0,
    "data": [
        {
            "date": "2021-04-01T00:00:00",
            "close": 365.5,
            "high": 370.649994,
            "low": 361.01001,
            "open": 362.410004,
            "vwma100day": 362.37086760000005,
            "vwma21day": 355.2388919047619,
            "vwma55day": 374.9623652727273
        },
        {
            "date": "2021-04-05T00:00:00",
            "close": 368.160004,
            "high": 369.170013,
            "low": 361.540009,
            "open": 367.5,
            "vwma100day": 362.44883430000004,
            "vwma21day": 355.53540047619043,
            "vwma55day": 375.10781999999995
        },
        {
            "date": "2021-04-06T00:00:00",
            "close": 373.0,
            "high": 378.700012,
            "low": 363.48999,
            "open": 363.48999,
            "vwma100day": 362.65620090000004,
            "vwma21day": 356.1134952380952,
            "vwma55day": 375.4035776363636
        },
        {
            "date": "2021-04-07T00:00:00",
            "close": 369.399994,
            "high": 373.690002,
            "low": 366.589996,
            "open": 373.570007,
            "vwma100day": 362.9963009,
            "vwma21day": 356.7784161904762,
            "vwma55day": 375.71351690909086
        },
        {
            "date": "2021-04-08T00:00:00",
            "close": 378.380005,
            "high": 382.269989,
            "low": 372.179993,
            "open": 377.320007,
            "vwma100day": 363.30413419999996,
            "vwma21day": 357.5333366666667,
            "vwma55day": 376.12024418181807
        },
        {
            "date": "2021-04-09T00:00:00",
            "close": 382.890015,
            "high": 383.170013,
            "low": 373.100006,
            "open": 378.399994,
            "vwma100day": 363.66800099999995,
            "vwma21day": 358.39857476190474,
            "vwma55day": 376.4220019999999
        },
        {
            "date": "2021-04-12T00:00:00",
            "close": 387.149994,
            "high": 388.640015,
            "low": 376.880005,
            "open": 380.269989,
            "vwma100day": 364.11803439999994,
            "vwma21day": 359.41143238095236,
            "vwma55day": 376.7412747272727
        },
        {
            "date": "2021-04-13T00:00:00",
            "close": 388.100006,
            "high": 390.190002,
            "low": 382.73999,
            "open": 384.299988,
            "vwma100day": 364.5966676999999,
            "vwma21day": 360.8423847619047,
            "vwma55day": 377.0542445454545
        },
        {
            "date": "2021-04-14T00:00:00",
            "close": 391.100006,
            "high": 393.480011,
            "low": 385.980011,
            "open": 389.040009,
            "vwma100day": 365.14440119999983,
            "vwma21day": 362.3441314285715,
            "vwma55day": 377.36763872727266
        },
        {
            "date": "2021-04-15T00:00:00",
            "close": 399.49,
            "high": 401.06,
            "low": 392.93,
            "open": 394.31,
            "vwma100day": 365.8139678999998,
            "vwma21day": 364.2217504761905,
            "vwma55day": 377.93709327272717
        },
        {
            "date": "2021-04-16T00:00:00",
            "close": 400.04,
            "high": 401.65,
            "low": 393.64,
            "open": 400.57,
            "vwma100day": 366.5007011999998,
            "vwma21day": 366.58540095238095,
            "vwma55day": 378.7581839999999
        },
        {
            "date": "2021-04-19T00:00:00",
            "close": 393.04,
            "high": 399.01,
            "low": 391.65,
            "open": 396.6,
            "vwma100day": 367.2340678999998,
            "vwma21day": 369.0973057142857,
            "vwma55day": 379.3481232727272
        },
        {
            "date": "2021-04-20T00:00:00",
            "close": 388.91,
            "high": 395.58,
            "low": 383.27,
            "open": 389.81,
            "vwma100day": 367.92420119999986,
            "vwma21day": 371.2803214285714,
            "vwma55day": 379.67569909090906
        },
        {
            "date": "2021-04-21T00:00:00",
            "close": 401.62,
            "high": 403.6,
            "low": 388.75,
            "open": 391.33,
            "vwma100day": 368.74130119999995,
            "vwma21day": 373.3311152380952,
            "vwma55day": 379.9893961818182
        },
        {
            "date": "2021-04-22T00:00:00",
            "close": 410.38,
            "high": 413.62,
            "low": 403.14,
            "open": 403.14,
            "vwma100day": 369.6861011999999,
            "vwma21day": 375.6071466666667,
            "vwma55day": 380.26612345454555
        },
        {
            "date": "2021-04-23T00:00:00",
            "close": 415.0,
            "high": 416.59,
            "low": 408.0,
            "open": 408.55,
            "vwma100day": 370.6518011999999,
            "vwma21day": 378.2538128571428,
            "vwma55day": 380.6893961818182
        },
        {
            "date": "2021-04-26T00:00:00",
            "close": 418.77,
            "high": 419.0,
            "low": 410.44,
            "open": 415.83,
            "vwma100day": 371.62920119999995,
            "vwma21day": 381.46444761904763,
            "vwma55day": 380.95618400000006
        },
        {
            "date": "2021-04-27T00:00:00",
            "close": 421.7,
            "high": 423.0,
            "low": 416.84,
            "open": 416.84,
            "vwma100day": 372.5810011999999,
            "vwma21day": 384.8757166666667,
            "vwma55day": 381.16388090909095
        },
        {
            "date": "2021-04-28T00:00:00",
            "close": 425.77,
            "high": 426.59,
            "low": 417.17,
            "open": 418.27,
            "vwma100day": 373.5138346,
            "vwma21day": 388.3679390476191,
            "vwma55day": 381.45848709090916
        },
        {
            "date": "2021-04-29T00:00:00",
            "close": 421.7,
            "high": 428.87,
            "low": 418.65,
            "open": 428.0,
            "vwma100day": 374.3280345,
            "vwma21day": 392.02397047619047,
            "vwma55day": 381.83654763636366
        },
        {
            "date": "2021-04-30T00:00:00",
            "close": 386.1,
            "high": 403.16,
            "low": 384.82,
            "open": 400.0,
            "vwma100day": 374.78780120000005,
            "vwma21day": 393.6619066666667,
            "vwma55day": 381.66703254545456
        },
        {
            "date": "2021-05-03T00:00:00",
            "close": 380.57,
            "high": 386.55,
            "low": 375.54,
            "open": 386.1,
            "vwma100day": 375.172768,
            "vwma21day": 394.38412904761907,
            "vwma55day": 381.1958205454546
        },
        {
            "date": "2021-05-04T00:00:00",
            "close": 371.42,
            "high": 378.97,
            "low": 366.29,
            "open": 378.63,
            "vwma100day": 375.46246809999997,
            "vwma21day": 394.6668271428572,
            "vwma55day": 380.64266927272723
        },
        {
            "date": "2021-05-05T00:00:00",
            "close": 365.94,
            "high": 374.14,
            "low": 360.79,
            "open": 371.99,
            "vwma100day": 375.75706809999997,
            "vwma21day": 394.4395257142857,
            "vwma55day": 379.93709345454533
        },
        {
            "date": "2021-05-06T00:00:00",
            "close": 357.34,
            "high": 362.88,
            "low": 350.76,
            "open": 360.75,
            "vwma100day": 375.9046348,
            "vwma21day": 393.82523999999995,
            "vwma55day": 378.9636387272726
        },
        {
            "date": "2021-05-07T00:00:00",
            "close": 358.74,
            "high": 370.38,
            "low": 358.5,
            "open": 362.57,
            "vwma100day": 376.06020149999995,
            "vwma21day": 393.107620952381,
            "vwma55day": 378.1195174545453
        },
        {
            "date": "2021-05-10T00:00:00",
            "close": 342.69,
            "high": 359.27,
            "low": 342.42,
            "open": 359.27,
            "vwma100day": 376.00623479999996,
            "vwma21day": 391.6031761904762,
            "vwma55day": 376.8801234545453
        },
        {
            "date": "2021-05-11T00:00:00",
            "close": 348.0,
            "high": 354.98,
            "low": 336.19,
            "open": 337.52,
            "vwma100day": 375.9481681,
            "vwma21day": 389.80158857142857,
            "vwma55day": 375.64406290909074
        },
        {
            "date": "2021-05-12T00:00:00",
            "close": 333.48,
            "high": 344.0,
            "low": 329.56,
            "open": 344.0,
            "vwma100day": 375.77813469999984,
            "vwma21day": 387.3573028571428,
            "vwma55day": 374.38369927272703
        },
        {
            "date": "2021-05-13T00:00:00",
            "close": 323.96,
            "high": 338.0,
            "low": 318.49,
            "open": 336.34,
            "vwma100day": 375.47963469999996,
            "vwma21day": 384.3396833333333,
            "vwma55day": 372.97612345454536
        },
        {
            "date": "2021-05-14T00:00:00",
            "close": 333.25,
            "high": 336.35,
            "low": 324.69,
            "open": 326.7,
            "vwma100day": 375.2021012999999,
            "vwma21day": 381.17793714285716,
            "vwma55day": 371.7781232727272
        },
        {
            "date": "2021-05-17T00:00:00",
            "close": 325.4,
            "high": 333.68,
            "low": 321.93,
            "open": 331.2,
            "vwma100day": 374.9707345999999,
            "vwma21day": 377.77603238095236,
            "vwma55day": 370.533396
        },
        {
            "date": "2021-05-18T00:00:00",
            "close": 330.11,
            "high": 337.48,
            "low": 328.87,
            "open": 329.99,
            "vwma100day": 374.7792345999998,
            "vwma21day": 374.8039685714285,
            "vwma55day": 369.3504263636363
        },
        {
            "date": "2021-05-19T00:00:00",
            "close": 332.29,
            "high": 332.9,
            "low": 323.0,
            "open": 323.47,
            "vwma100day": 374.48333469999983,
            "vwma21day": 371.9536514285714,
            "vwma55day": 368.2029112727273
        },
        {
            "date": "2021-05-20T00:00:00",
            "close": 344.3,
            "high": 345.76,
            "low": 333.7,
            "open": 336.08,
            "vwma100day": 374.34580139999986,
            "vwma21day": 369.25190523809516,
            "vwma55day": 367.6190929090909
        },
        {
            "date": "2021-05-21T00:00:00",
            "close": 342.09,
            "high": 351.5,
            "low": 341.56,
            "open": 344.59,
            "vwma100day": 374.1961013999999,
            "vwma21day": 366.2044447619047,
            "vwma55day": 367.34612327272725
        },
        {
            "date": "2021-05-24T00:00:00",
            "close": 355.39,
            "high": 363.01,
            "low": 343.74,
            "open": 346.74,
            "vwma100day": 374.14276819999986,
            "vwma21day": 363.38777809523805,
            "vwma55day": 367.24533527272723
        },
        {
            "date": "2021-05-25T00:00:00",
            "close": 353.25,
            "high": 359.22,
            "low": 352.83,
            "open": 354.79,
            "vwma100day": 374.0939015999998,
            "vwma21day": 360.48444476190474,
            "vwma55day": 367.2302445454545
        },
        {
            "date": "2021-05-26T00:00:00",
            "close": 354.69,
            "high": 357.98,
            "low": 348.92,
            "open": 349.59,
            "vwma100day": 373.95950159999984,
            "vwma21day": 357.3106352380952,
            "vwma55day": 367.08672927272727
        },
        {
            "date": "2021-05-27T00:00:00",
            "close": 361.91,
            "high": 363.0,
            "low": 348.28,
            "open": 353.62,
            "vwma100day": 373.93996829999975,
            "vwma21day": 354.1941271428571,
            "vwma55day": 367.01727454545454
        },
        {
            "date": "2021-05-28T00:00:00",
            "close": 369.39,
            "high": 378.44,
            "low": 368.03,
            "open": 375.0,
            "vwma100day": 374.01096829999983,
            "vwma21day": 351.7598414285714,
            "vwma55day": 367.18091090909087
        },
        {
            "date": "2021-06-01T00:00:00",
            "close": 365.67,
            "high": 374.33,
            "low": 361.58,
            "open": 371.2,
            "vwma100day": 373.9258348999998,
            "vwma21day": 350.60904761904766,
            "vwma55day": 367.3669714545455
        },
        {
            "date": "2021-06-02T00:00:00",
            "close": 370.99,
            "high": 372.41,
            "low": 363.04,
            "open": 365.31,
            "vwma100day": 373.76910149999986,
            "vwma21day": 350.03412666666674,
            "vwma55day": 367.55175927272734
        },
        {
            "date": "2021-06-03T00:00:00",
            "close": 376.74,
            "high": 378.79,
            "low": 366.99,
            "open": 366.99,
            "vwma100day": 373.62303479999986,
            "vwma21day": 350.1268247619048,
            "vwma55day": 367.83860763636363
        },
        {
            "date": "2021-06-04T00:00:00",
            "close": 382.91,
            "high": 387.95,
            "low": 378.35,
            "open": 379.52,
            "vwma100day": 373.7560346999999,
            "vwma21day": 350.89412619047624,
            "vwma55day": 368.4615772727273
        },
        {
            "date": "2021-06-07T00:00:00",
            "close": 386.98,
            "high": 392.0,
            "low": 380.76,
            "open": 384.01,
            "vwma100day": 373.99536789999996,
            "vwma21day": 352.3030152380953,
            "vwma55day": 369.2754560000001
        },
        {
            "date": "2021-06-08T00:00:00",
            "close": 389.95,
            "high": 393.31,
            "low": 384.62,
            "open": 388.29,
            "vwma100day": 374.3054012,
            "vwma21day": 353.5769833333334,
            "vwma55day": 370.10969836363637
        },
        {
            "date": "2021-06-09T00:00:00",
            "close": 390.03,
            "high": 398.15,
            "low": 389.57,
            "open": 395.0,
            "vwma100day": 374.6766012,
            "vwma21day": 355.6939671428573,
            "vwma55day": 370.79442563636366
        },
        {
            "date": "2021-06-10T00:00:00",
            "close": 398.98,
            "high": 399.68,
            "low": 387.03,
            "open": 390.4,
            "vwma100day": 375.10043450000006,
            "vwma21day": 358.0196814285715,
            "vwma55day": 371.41224363636366
        },
        {
            "date": "2021-06-11T00:00:00",
            "close": 400.19,
            "high": 401.91,
            "low": 396.52,
            "open": 401.09,
            "vwma100day": 375.5434345000001,
            "vwma21day": 361.0606338095239,
            "vwma55day": 372.17448581818184
        },
        {
            "date": "2021-06-14T00:00:00",
            "close": 409.09,
            "high": 409.72,
            "low": 399.19,
            "open": 400.31,
            "vwma100day": 375.9722012,
            "vwma21day": 364.83126857142867,
            "vwma55day": 373.2172736363637
        },
        {
            "date": "2021-06-15T00:00:00",
            "close": 405.1,
            "high": 415.44,
            "low": 404.0,
            "open": 410.0,
            "vwma100day": 376.3873678,
            "vwma21day": 368.4860304761906,
            "vwma55day": 374.2955158181818
        },
        {
            "date": "2021-06-16T00:00:00",
            "close": 403.75,
            "high": 408.72,
            "low": 397.99,
            "open": 405.8,
            "vwma100day": 376.7242679,
            "vwma21day": 372.1280942857144,
            "vwma55day": 375.27090981818174
        },
        {
            "date": "2021-06-17T00:00:00",
            "close": 412.45,
            "high": 417.42,
            "low": 400.08,
            "open": 402.82,
            "vwma100day": 377.09460119999994,
            "vwma21day": 375.8342847619048,
            "vwma55day": 376.42884909090895
        },
        {
            "date": "2021-06-18T00:00:00",
            "close": 418.29,
            "high": 419.19,
            "low": 411.12,
            "open": 411.91,
            "vwma100day": 377.59153449999997,
            "vwma21day": 379.96777666666674,
            "vwma55day": 377.50587927272716
        },
        {
            "date": "2021-06-21T00:00:00",
            "close": 423.03,
            "high": 424.28,
            "low": 407.62,
            "open": 418.29,
            "vwma100day": 378.2418010999999,
            "vwma21day": 383.63714190476196,
            "vwma55day": 378.462061090909
        },
        {
            "date": "2021-06-22T00:00:00",
            "close": 427.51,
            "high": 427.59,
            "low": 418.07,
            "open": 420.88,
            "vwma100day": 378.86450099999985,
            "vwma21day": 387.4152371428571,
            "vwma55day": 379.51842454545437
        },
        {
            "date": "2021-06-23T00:00:00",
            "close": 431.72,
            "high": 433.1,
            "low": 423.26,
            "open": 427.85,
            "vwma100day": 379.4457343999999,
            "vwma21day": 391.00158619047625,
            "vwma55day": 380.56624272727265
        },
        {
            "date": "2021-06-24T00:00:00",
            "close": 425.0,
            "high": 439.24,
            "low": 424.67,
            "open": 433.2,
            "vwma100day": 379.9347344999998,
            "vwma21day": 394.55095142857147,
            "vwma55day": 381.6524852727272
        },
        {
            "date": "2021-06-25T00:00:00",
            "close": 430.36,
            "high": 430.48,
            "low": 419.63,
            "open": 425.6,
            "vwma100day": 380.2647010999998,
            "vwma21day": 398.0252371428571,
            "vwma55day": 382.547273090909
        },
        {
            "date": "2021-06-28T00:00:00",
            "close": 427.16,
            "high": 431.58,
            "low": 422.45,
            "open": 431.49,
            "vwma100day": 380.6361676999999,
            "vwma21day": 401.32682428571434,
            "vwma55day": 383.40806072727264
        },
        {
            "date": "2021-06-29T00:00:00",
            "close": 426.8,
            "high": 427.37,
            "low": 418.85,
            "open": 425.75,
            "vwma100day": 380.86560099999986,
            "vwma200day": 373.00651690000007,
            "vwma21day": 403.82142761904765,
            "vwma55day": 384.13745454545443
        },
        {
            "date": "2021-06-30T00:00:00",
            "close": 427.0,
            "high": 427.89,
            "low": 422.49,
            "open": 424.54,
            "vwma100day": 381.0326343,
            "vwma200day": 373.16975020000007,
            "vwma21day": 406.6119038095238,
            "vwma55day": 384.842606
        },
        {
            "date": "2021-07-01T00:00:00",
            "close": 426.84,
            "high": 428.02,
            "low": 420.74,
            "open": 424.99,
            "vwma100day": 381.21490099999994,
            "vwma200day": 373.31168355,
            "vwma21day": 409.29698333333334,
            "vwma55day": 385.4792118181818
        },
        {
            "date": "2021-07-02T00:00:00",
            "close": 431.59,
            "high": 432.96,
            "low": 426.2,
            "open": 428.46,
            "vwma100day": 381.494601,
            "vwma200day": 373.48058355,
            "vwma21day": 411.967300952381,
            "vwma55day": 386.06872690909097
        },
        {
            "date": "2021-07-06T00:00:00",
            "close": 440.65,
            "high": 442.55,
            "low": 428.13,
            "open": 432.05,
            "vwma100day": 381.85886769999996,
            "vwma200day": 373.74708355,
            "vwma21day": 414.5406342857143,
            "vwma55day": 386.7717572727273
        },
        {
            "date": "2021-07-07T00:00:00",
            "close": 447.52,
            "high": 449.11,
            "low": 437.13,
            "open": 444.48,
            "vwma100day": 382.2367011,
            "vwma200day": 374.01771690000004,
            "vwma21day": 417.3028566666667,
            "vwma55day": 387.68121181818185
        },
        {
            "date": "2021-07-08T00:00:00",
            "close": 446.97,
            "high": 447.33,
            "low": 436.22,
            "open": 440.63,
            "vwma100day": 382.6452679,
            "vwma200day": 374.2909836000001,
            "vwma21day": 419.8844442857143,
            "vwma55day": 388.6676361818183
        },
        {
            "date": "2021-07-09T00:00:00",
            "close": 440.73,
            "high": 445.49,
            "low": 436.29,
            "open": 445.12,
            "vwma100day": 382.9960012,
            "vwma200day": 374.53103360000017,
            "vwma21day": 422.1822223809524,
            "vwma55day": 389.4466665454546
        },
        {
            "date": "2021-07-12T00:00:00",
            "close": 445.77,
            "high": 448.67,
            "low": 441.53,
            "open": 445.42,
            "vwma100day": 383.3439011,
            "vwma200day": 374.81231690000016,
            "vwma21day": 424.56761904761913,
            "vwma55day": 390.10624218181823
        },
        {
            "date": "2021-07-13T00:00:00",
            "close": 446.39,
            "high": 449.82,
            "low": 442.03,
            "open": 445.38,
            "vwma100day": 383.7150344,
            "vwma200day": 375.1316669000002,
            "vwma21day": 426.78380952380957,
            "vwma55day": 390.704120909091
        },
        {
            "date": "2021-07-14T00:00:00",
            "close": 440.49,
            "high": 449.74,
            "low": 438.84,
            "open": 448.49,
            "vwma100day": 383.9823343,
            "vwma200day": 375.3773502500002,
            "vwma21day": 428.54682523809527,
            "vwma55day": 391.1941814545455
        },
        {
            "date": "2021-07-15T00:00:00",
            "close": 441.42,
            "high": 442.07,
            "low": 433.91,
            "open": 438.94,
            "vwma100day": 384.2299343,
            "vwma200day": 375.5918502000002,
            "vwma21day": 430.0207933333334,
            "vwma55day": 391.53272690909097
        },
        {
            "date": "2021-07-16T00:00:00",
            "close": 448.69,
            "high": 451.43,
            "low": 440.97,
            "open": 442.55,
            "vwma100day": 384.6502343,
            "vwma200day": 375.81061685000014,
            "vwma21day": 432.0942852380952,
            "vwma55day": 391.96642381818185
        },
        {
            "date": "2021-07-19T00:00:00",
            "close": 435.05,
            "high": 451.47,
            "low": 431.99,
            "open": 444.12,
            "vwma100day": 385.00293419999997,
            "vwma200day": 375.9660834500001,
            "vwma21day": 433.49999952380955,
            "vwma55day": 392.2651510909091
        },
        {
            "date": "2021-07-20T00:00:00",
            "close": 447.7,
            "high": 451.33,
            "low": 431.15,
            "open": 434.88,
            "vwma100day": 385.46366739999996,
            "vwma200day": 376.1102668000001,
            "vwma21day": 434.79491999999993,
            "vwma55day": 393.21121163636366
        },
        {
            "date": "2021-07-21T00:00:00",
            "close": 446.98,
            "high": 449.8,
            "low": 437.14,
            "open": 449.49,
            "vwma100day": 385.9554341,
            "vwma200day": 376.3914168500001,
            "vwma21day": 436.0487295238095,
            "vwma55day": 394.37036309090917
        },
        {
            "date": "2021-07-22T00:00:00",
            "close": 450.89,
            "high": 452.76,
            "low": 446.14,
            "open": 448.76,
            "vwma100day": 386.4825675,
            "vwma200day": 376.72271685000015,
            "vwma21day": 437.26491999999996,
            "vwma55day": 395.78315090909086
        },
        {
            "date": "2021-07-23T00:00:00",
            "close": 460.72,
            "high": 463.2,
            "low": 450.37,
            "open": 452.65,
            "vwma100day": 387.13843419999995,
            "vwma200day": 377.1171168500001,
            "vwma21day": 438.63333285714276,
            "vwma55day": 397.4402418181818
        },
        {
            "date": "2021-07-26T00:00:00",
            "close": 452.58,
            "high": 458.79,
            "low": 450.74,
            "open": 458.79,
            "vwma100day": 387.94516749999997,
            "vwma200day": 377.44563355000014,
            "vwma21day": 439.79523761904755,
            "vwma55day": 399.2046661818181
        },
        {
            "date": "2021-07-27T00:00:00",
            "close": 448.58,
            "high": 454.58,
            "low": 445.27,
            "open": 452.29,
            "vwma100day": 388.83930089999996,
            "vwma200day": 377.73556690000004,
            "vwma21day": 440.87396809523807,
            "vwma55day": 400.7853329090908
        },
        {
            "date": "2021-07-28T00:00:00",
            "close": 459.92,
            "high": 461.0,
            "low": 447.6,
            "open": 448.56,
            "vwma100day": 389.8051341,
            "vwma200day": 378.0694668500001,
            "vwma21day": 442.2601585714285,
            "vwma55day": 402.74981763636356
        },
        {
            "date": "2021-07-29T00:00:00",
            "close": 456.05,
            "high": 466.12,
            "low": 455.45,
            "open": 459.64,
            "vwma100day": 390.8379009000001,
            "vwma200day": 378.39211690000013,
            "vwma21day": 443.9204761904761,
            "vwma55day": 404.8010298181818
        }
    ]
}